odoo/addons/stock_orderpoint_automatic_creation/README.rst
odoo/addons/stock_orderpoint_automatic_creation/__init__.py
odoo/addons/stock_orderpoint_automatic_creation/__manifest__.py
odoo/addons/stock_orderpoint_automatic_creation/i18n/ca.po
odoo/addons/stock_orderpoint_automatic_creation/i18n/cs_CZ.po
odoo/addons/stock_orderpoint_automatic_creation/i18n/de.po
odoo/addons/stock_orderpoint_automatic_creation/i18n/el_GR.po
odoo/addons/stock_orderpoint_automatic_creation/i18n/es.po
odoo/addons/stock_orderpoint_automatic_creation/i18n/es_ES.po
odoo/addons/stock_orderpoint_automatic_creation/i18n/es_MX.po
odoo/addons/stock_orderpoint_automatic_creation/i18n/eu.po
odoo/addons/stock_orderpoint_automatic_creation/i18n/fi.po
odoo/addons/stock_orderpoint_automatic_creation/i18n/fr.po
odoo/addons/stock_orderpoint_automatic_creation/i18n/fr_CH.po
odoo/addons/stock_orderpoint_automatic_creation/i18n/fr_FR.po
odoo/addons/stock_orderpoint_automatic_creation/i18n/gl.po
odoo/addons/stock_orderpoint_automatic_creation/i18n/hr.po
odoo/addons/stock_orderpoint_automatic_creation/i18n/hr_HR.po
odoo/addons/stock_orderpoint_automatic_creation/i18n/it.po
odoo/addons/stock_orderpoint_automatic_creation/i18n/nl.po
odoo/addons/stock_orderpoint_automatic_creation/i18n/nl_NL.po
odoo/addons/stock_orderpoint_automatic_creation/i18n/pt.po
odoo/addons/stock_orderpoint_automatic_creation/i18n/pt_BR.po
odoo/addons/stock_orderpoint_automatic_creation/i18n/ro.po
odoo/addons/stock_orderpoint_automatic_creation/i18n/ru.po
odoo/addons/stock_orderpoint_automatic_creation/i18n/sl.po
odoo/addons/stock_orderpoint_automatic_creation/i18n/stock_orderpoint_automatic_creation.pot
odoo/addons/stock_orderpoint_automatic_creation/i18n/tr.po
odoo/addons/stock_orderpoint_automatic_creation/i18n/tr_TR.po
odoo/addons/stock_orderpoint_automatic_creation/i18n/vi_VN.po
odoo/addons/stock_orderpoint_automatic_creation/i18n/zh_CN.po
odoo/addons/stock_orderpoint_automatic_creation/models/__init__.py
odoo12_addon_stock_orderpoint_automatic_creation-12.0.1.0.2.dist-info/METADATA
odoo12_addon_stock_orderpoint_automatic_creation-12.0.1.0.2.dist-info/WHEEL
odoo12_addon_stock_orderpoint_automatic_creation-12.0.1.0.2.dist-info/top_level.txt
odoo12_addon_stock_orderpoint_automatic_creation-12.0.1.0.2.dist-info/RECORD
